haobtc_oauth2-0.0.6.dist-info/DESCRIPTION.rst
haobtc_oauth2-0.0.6.dist-info/METADATA
haobtc_oauth2-0.0.6.dist-info/RECORD
haobtc_oauth2-0.0.6.dist-info/WHEEL
haobtc_oauth2-0.0.6.dist-info/metadata.json
haobtc_oauth2-0.0.6.dist-info/top_level.txt
pyoauth2/__init__.py
pyoauth2/client.py
pyoauth2/libs/__init__.py
pyoauth2/libs/access_token.py
pyoauth2/libs/auth_code.py
pyoauth2/libs/base.py
pyoauth2/libs/connection.py
pyoauth2/libs/errors.py
pyoauth2/libs/request.py
pyoauth2/libs/response.py
pyoauth2/libs/utils.py
